zs_mixins/__init__.py
zs_mixins-0.0.1.dist-info/LICENSE
zs_mixins-0.0.1.dist-info/WHEEL
zs_mixins-0.0.1.dist-info/METADATA
zs_mixins-0.0.1.dist-info/RECORD
