Metadata-Version: 2.1
Name: zs-mixins
Version: 0.0.1
Summary: 
Author: codeif
Author-email: me@codeif.com
Requires-Python: >=3.8,<4.0
Classifier: Programming Language :: Python :: 3
Classifier: Programming Language :: Python :: 3.10
Classifier: Programming Language :: Python :: 3.8
Classifier: Programming Language :: Python :: 3.9
Requires-Dist: SQLAlchemy (>=1.3)
Requires-Dist: Werkzeug (>=2.0)
